devel/__init__.py
devel/create_dicomdir_pilsen_pigs.py
devel/doc_decorator.py
devel/export_to_jpg.py
devel/itkread.py
devel/dataset/__init__.py
devel/dataset/transform_file_structure.py
devel/dataset/transform_file_structure_test.py
io3d/__init__.py
io3d/__main__.py
io3d/anonym.py
io3d/cachefile.py
io3d/connect.py
io3d/connector.py
io3d/convert_coco_ann_to_mask.py
io3d/datareader.py
io3d/datareaderqt.py
io3d/datasets.py
io3d/datasets_create.py
io3d/datawriter.py
io3d/dcmreaddata.py
io3d/dcmtools.py
io3d/deprecation.py
io3d/dicomdir.py
io3d/dili_subset.py
io3d/dilipg.py
io3d/files.py
io3d/fsbrowser.py
io3d/hdf5_io.py
io3d/idxformat.py
io3d/image.py
io3d/image_manipulation.py
io3d/misc.py
io3d/network.py
io3d/nifti_io.py
io3d/outputqt.py
io3d/rawN.py
io3d/tgz.py
io3d-2.10.6.dist-info/LICENSE
io3d-2.10.6.dist-info/METADATA
io3d-2.10.6.dist-info/WHEEL
io3d-2.10.6.dist-info/top_level.txt
io3d-2.10.6.dist-info/RECORD
