Metadata-Version: 2.1
Name: io3d
Version: 2.10.6
Summary: 3D data read and write
Home-page: https://github.com/mjirik/io3d
Author: Miroslav Jirik
Author-email: miroslav.jirik@gmail.com
License: MIT
Keywords: dicom 3D read write
Platform: UNKNOWN
Classifier: Development Status :: 3 - Alpha
Classifier: Intended Audience :: Developers
Classifier: Topic :: Scientific/Engineering :: Bio-Informatics
Classifier: License :: OSI Approved :: BSD License
Classifier: Programming Language :: Python :: 3.6
Classifier: Programming Language :: Python :: 3.7
License-File: LICENSE
